{
    "afr_Latn": "Afrikaans",
    "amh_Ethi": "Amharique",
    "ara_Arab": "Arabe",
    "asm_Beng": "Assamais",
    "ast_Latn": "Asturien",
    "azj_Latn": "Azéri",
    "bel_Cyrl": "Biélorusse",
    "ben_Beng": "Bengali",
    "bos_Latn": "Bosnien",
    "bul_Cyrl": "Bulgare",
    "cat_Latn": "Catalan",
    "ceb_Latn": "Cebuano",
    "ces_Latn": "Tchèque",
    "ckb_Arab": "Kurde (Sorani)",
    "cym_Latn": "Gallois",
    "dan_Latn": "Danois",
    "deu_Latn": "Allemand",
    "ell_Grek": "Grec",
    "eng_Latn": "Anglais",
    "est_Latn": "Estonien",
    "fin_Latn": "Finnois",
    "fra_Latn": "Français",
    "fuv_Latn": "Fulfulde",
    "gaz_Latn": "Gayo",
    "gle_Latn": "Irlandais",
    "glg_Latn": "Galicien",
    "guj_Gujr": "Gujarati",
    "hat_Latn": "Créole haïtien",
    "hau_Latn": "Haoussa",
    "heb_Hebr": "Hébreu",
    "hin_Deva": "Hindi",
    "hrv_Latn": "Croate",
    "hun_Latn": "Hongrois",
    "hye_Armn": "Arménien",
    "ibo_Latn": "Igbo",
    "ind_Latn": "Indonésien",
    "isl_Latn": "Islandais",
    "ita_Latn": "Italien",
    "jav_Latn": "Javanais",
    "jpn_Jpan": "Japonais",
    "kam_Latn": "Kamba",
    "kan_Knda": "Kannada",
    "kat_Geor": "Géorgien",
    "kaz_Cyrl": "Kazakh",
    "kea_Latn": "Créole du Cap-Vert",
    "khk_Cyrl": "Khalkha Mongol",
    "khm_Khmr": "Khmer",
    "kir_Cyrl": "Kirghiz",
    "kor_Hang": "Coréen",
    "lao_Laoo": "Lao",
    "lit_Latn": "Lituanien",
    "ltz_Latn": "Luxembourgeois",
    "lug_Latn": "Ganda",
    "luo_Latn": "Luo",
    "lvs_Latn": "Letton",
    "mai_Deva": "Maithili",
    "mal_Mlym": "Malayalam",
    "mar_Deva": "Marathi",
    "mkd_Cyrl": "Macédonien",
    "mlt_Latn": "Maltais",
    "mni_Beng": "Manipuri",
    "mya_Mymr": "Birman",
    "nld_Latn": "Néerlandais",
    "nno_Latn": "Norvégien (Nynorsk)",
    "nob_Latn": "Norvégien (Bokmål)",
    "npi_Deva": "Népalais",
    "nya_Latn": "Chichewa",
    "ory_Orya": "Odia",
    "pan_Guru": "Pendjabi",
    "pbt_Arab": "Pachtou",
    "pes_Arab": "Persan",
    "pol_Latn": "Polonais",
    "por_Latn": "Portugais",
    "ron_Latn": "Roumain",
    "rus_Cyrl": "Russe",
    "slk_Latn": "Slovaque",
    "slv_Latn": "Slovène",
    "sna_Latn": "Shona",
    "snd_Arab": "Sindhi",
    "som_Latn": "Somali",
    "spa_Latn": "Espagnol",
    "srp_Cyrl": "Serbe",
    "swe_Latn": "Suédois",
    "swh_Latn": "Swahili",
    "tam_Taml": "Tamoul",
    "tel_Telu": "Télougou",
    "tgk_Cyrl": "Tadjik",
    "tgl_Latn": "Tagalog",
    "tha_Thai": "Thaï",
    "tur_Latn": "Turc",
    "ukr_Cyrl": "Ukrainien",
    "urd_Arab": "Ourdou",
    "uzn_Latn": "Ouzbek",
    "vie_Latn": "Vietnamien",
    "xho_Latn": "Xhosa",
    "yor_Latn": "Yoruba",
    "zho_Hans": "Chinois simplifié",
    "zho_Hant": "Chinois traditionnel",
    "zsm_Latn": "Malais",
    "zul_Latn": "Zoulou"
}